eve_simple_esi/__init__.py
eve_simple_esi-0.0.6.dist-info/LICENSE
eve_simple_esi-0.0.6.dist-info/METADATA
eve_simple_esi-0.0.6.dist-info/WHEEL
eve_simple_esi-0.0.6.dist-info/top_level.txt
eve_simple_esi-0.0.6.dist-info/RECORD
