Metadata-Version: 2.1
Name: eve-simple-esi
Version: 0.0.6
Summary: The Python 3+ library for simple and fast work with https://esi.evetech.net data.
Home-page: https://github.com/drdanio/eve-simple-esi
Author: Zorg Programming
Author-email: dr.danio@gmail.com
License: UNKNOWN
Platform: UNKNOWN
Classifier: Programming Language :: Python :: 3
Classifier: License :: OSI Approved :: MIT License
Classifier: Operating System :: OS Independent
Requires-Python: >=3.6
